lortools/__init__.py
lortools/sandbox.py
lortools/array/__init__.py
lortools/array/binary_array.py
lortools/search/__init__.py
lortools/search/binary_search.py
lortools/sort/__init__.py
lortools/sort/sort_tools.py
lortools/tests/__init__.py
lortools/tests/unittests.py
lortools-1.0.0.dist-info/LICENSE.md
lortools-1.0.0.dist-info/METADATA
lortools-1.0.0.dist-info/WHEEL
lortools-1.0.0.dist-info/top_level.txt
lortools-1.0.0.dist-info/RECORD
