Metadata-Version: 2.1
Name: lortools
Version: 1.0.0
Summary: LorTools: A Collection of Nifty Sort And Search Tools.
Author: Laurent Mertens
Maintainer: Laurent Mertens
License: Copyright (c) 2024 Laurent Mertens
Project-URL: Homepage, https://github.com/LaurentMertens/LorTools
Keywords: Binary search
Requires-Python: >=3.6
License-File: LICENSE.md
